LICENSE.txt
MANIFEST.in
README.rst
setup.py
js/__init__.py
js.angular.egg-info/PKG-INFO
js.angular.egg-info/SOURCES.txt
js.angular.egg-info/dependency_links.txt
js.angular.egg-info/entry_points.txt
js.angular.egg-info/namespace_packages.txt
js.angular.egg-info/not-zip-safe
js.angular.egg-info/requires.txt
js.angular.egg-info/top_level.txt
js/angular/__init__.py
js/angular/test_angularjs.txt
js/angular/resources/.angular-mobile.js.swp
js/angular/resources/angular-bootstrap-prettify.js
js/angular/resources/angular-bootstrap-prettify.min.js
js/angular/resources/angular-bootstrap.js
js/angular/resources/angular-bootstrap.min.js
js/angular/resources/angular-cookies.js
js/angular/resources/angular-cookies.min.js
js/angular/resources/angular-loader.js
js/angular/resources/angular-loader.min.js
js/angular/resources/angular-mobile.js
js/angular/resources/angular-mobile.min.js
js/angular/resources/angular-mocks.js
js/angular/resources/angular-resource.js
js/angular/resources/angular-resource.min.js
js/angular/resources/angular-sanitize.js
js/angular/resources/angular-sanitize.min.js
js/angular/resources/angular-scenario.js
js/angular/resources/angular.js
js/angular/resources/angular.min.js
js/angular/resources/i18n/angular-locale_af-na.js
js/angular/resources/i18n/angular-locale_af-za.js
js/angular/resources/i18n/angular-locale_af.js
js/angular/resources/i18n/angular-locale_am-et.js
js/angular/resources/i18n/angular-locale_am.js
js/angular/resources/i18n/angular-locale_ar-001.js
js/angular/resources/i18n/angular-locale_ar-ae.js
js/angular/resources/i18n/angular-locale_ar-bh.js
js/angular/resources/i18n/angular-locale_ar-dz.js
js/angular/resources/i18n/angular-locale_ar-eg.js
js/angular/resources/i18n/angular-locale_ar-iq.js
js/angular/resources/i18n/angular-locale_ar-jo.js
js/angular/resources/i18n/angular-locale_ar-kw.js
js/angular/resources/i18n/angular-locale_ar-lb.js
js/angular/resources/i18n/angular-locale_ar-ly.js
js/angular/resources/i18n/angular-locale_ar-ma.js
js/angular/resources/i18n/angular-locale_ar-om.js
js/angular/resources/i18n/angular-locale_ar-qa.js
js/angular/resources/i18n/angular-locale_ar-sa.js
js/angular/resources/i18n/angular-locale_ar-sd.js
js/angular/resources/i18n/angular-locale_ar-sy.js
